schedulers/__init__.py
schedulers/cosine_lr.py
schedulers/linear_lr.py
flow_utils-0.0.1.dist-info/LICENSE
flow_utils-0.0.1.dist-info/METADATA
flow_utils-0.0.1.dist-info/WHEEL
flow_utils-0.0.1.dist-info/top_level.txt
flow_utils-0.0.1.dist-info/RECORD
