Metadata-Version: 2.1
Name: flow-utils
Version: 0.0.1
Summary: deeplearning utils based on OneFlow
Home-page: https://github.com/rentainhe/oneflow-utils.git
Author: Ren Tianhe
Author-email: 596106517@qq.com
License: UNKNOWN
Platform: UNKNOWN
Classifier: Programming Language :: Python :: 3
Classifier: License :: OSI Approved :: MIT License
Classifier: Operating System :: OS Independent
License-File: LICENSE
